[{"id":215951,"league":{"id":71,"name":"UEFA European U19 Championship","country":"Europe","is_women":false,"current_season":{"id":1522,"name":"U19 European Championship 2026","year":2026,"start_date":"2026-01-01","end_date":"2026-12-31"}},"home_team":"Spain U19","away_team":"Germany U19","home_team_obj":{"id":3918,"name":"Spain U19","short_name":"Spain U19","country":"Spain","coach":{"name":"Paco Gallardo","shortName":"P. Gallardo"},"venue":null},"away_team_obj":{"id":3919,"name":"Germany U19","short_name":"Germany U19","country":"Germany","coach":{"name":"Christian Worns","shortName":"C. Worns"},"venue":null},"event_date":"2026-07-11T22:00:00+04:00","group_name":"Group A","status":"2nd_half","home_score":2,"away_score":0,"home_score_ht":1,"away_score_ht":0,"penalty_shootout":null,"extra_time_score":null,"current_minute":82,"period":"2T","home_xg_live":null,"away_xg_live":null,"incidents":[{"text":"Second half","type":"period","minute":90,"is_live":true,"added_time":999,"away_score":0,"home_score":2},{"type":"substitution","minute":73,"is_home":true,"player_in":"D. Z. Hidalgo","added_time":null,"player_out":"X. Espart","player_in_id":1614682,"player_out_id":1546073},{"type":"substitution","minute":73,"is_home":true,"player_in":"A. Antañón","added_time":null,"player_out":"Q. Junyent","player_in_id":1916256,"player_out_id":1580030},{"type":"card","minute":67,"player":"X. Espart","is_home":true,"card_type":"yellow","player_id":1546073,"added_time":null},{"type":"substitution","minute":64,"is_home":false,"player_in":"L. Engelns","added_time":null,"player_out":"B. Nink","player_in_id":1838178,"player_out_id":1536452},{"type":"substitution","minute":64,"is_home":false,"player_in":"T. Poller","added_time":null,"player_out":"O. Stange","player_in_id":1568541,"player_out_id":1568535},{"type":"substitution","minute":64,"is_home":true,"player_in":"O. Diallo","added_time":null,"player_out":"D. Yañez","player_in_id":1542807,"player_out_id":1546404},{"type":"substitution","minute":64,"is_home":true,"player_in":"S. Esteban","added_time":null,"player_out":"H. Lopez","player_in_id":1939329,"player_out_id":1966890},{"type":"card","minute":60,"player":"J. Fields","is_home":false,"card_type":"yellow","player_id":1961852,"added_time":null},{"type":"substitution","minute":59,"is_home":false,"player_in":"J. Fields","added_time":null,"player_out":"M. Reimers","player_in_id":1961852,"player_out_id":1995005},{"type":"goal","assist":"D. Yañez","minute":48,"player":"M. Rivas","is_home":true,"sequence":[{"end":{"x":96.5,"y":46.8},"pid":1546404,"pos":{"x":99.5,"y":0.5},"event":"cross","assist":true,"player":"D. Yañez"},{"gk":{"x":99.3,"y":48.9},"gm":{"x":70.97,"y":70.5},"pid":1542791,"pos":{"x":96.5,"y":46.8},"body":"head","event":"goal","player":"M. Rivas"}],"goal_type":"regular","player_id":1542791,"added_time":null,"away_score":0,"home_score":2},{"text":"HT","type":"period","minute":45,"is_live":false,"added_time":999,"away_score":0,"home_score":1},{"type":"injuryTime","length":3,"minute":45},{"type":"goal","minute":44,"player":"H. Lopez","is_home":true,"sequence":[{"gk":{"x":99.3,"y":51.4},"gm":{"x":48.92,"y":95.83},"pid":1966890,"pos":{"x":96.7,"y":50.2},"body":"right-foot","event":"goal","player":"H. Lopez"}],"goal_type":"regular","player_id":1966890,"added_time":null,"away_score":0,"home_score":1}],"live_stats":{"away":{"duels":48,"fouls":11,"passes":278,"crosses":"4/12 (33%)","punches":0,"tackles":14,"dribbles":"3/13 (23%)","offsides":0,"big_saves":1,"throw_ins":21,"clearances":17,"free_kicks":13,"goal_kicks":12,"long_balls":"12/34 (35%)","recoveries":36,"big_chances":1,"high_claims":0,"tackles_won":36,"total_saves":1,"total_shots":11,"aerial_duels":"7/12 (58%)","corner_kicks":2,"dispossessed":8,"ground_duels":"30/65 (46%)","hit_woodwork":1,"yellow_cards":1,"blocked_shots":4,"interceptions":7,"through_balls":1,"total_tackles":14,"accurate_passes":219,"ball_possession":36,"shots_on_target":4,"goalkeeper_saves":1,"shots_inside_box":7,"shots_off_target":3,"final_third_phase":"30/44 (68%)","shots_outside_box":4,"big_chances_missed":1,"big_chances_scored":0,"final_third_entries":31,"fouled_in_final_third":1,"touches_in_penalty_area":10},"home":{"duels":52,"fouls":13,"passes":521,"crosses":"3/13 (23%)","punches":1,"tackles":18,"dribbles":"6/13 (46%)","offsides":1,"big_saves":0,"throw_ins":16,"clearances":19,"free_kicks":11,"goal_kicks":4,"long_balls":"19/35 (54%)","recoveries":50,"big_chances":2,"high_claims":1,"tackles_won":61,"total_saves":4,"total_shots":13,"aerial_duels":"5/12 (42%)","corner_kicks":8,"dispossessed":7,"ground_duels":"35/65 (54%)","hit_woodwork":2,"yellow_cards":1,"blocked_shots":5,"interceptions":6,"through_balls":1,"total_tackles":18,"accurate_passes":459,"ball_possession":64,"shots_on_target":3,"goalkeeper_saves":4,"shots_inside_box":7,"shots_off_target":5,"final_third_phase":"157/192 (82%)","shots_outside_box":6,"big_chances_missed":0,"big_chances_scored":2,"final_third_entries":77,"fouled_in_final_third":2,"touches_in_penalty_area":21},"first_half":{"away":{"duels":55,"fouls":5,"passes":138,"crosses":"1/7 (14%)","tackles":11,"dribbles":"3/8 (38%)","offsides":0,"throw_ins":12,"clearances":11,"free_kicks":7,"goal_kicks":6,"long_balls":"5/20 (25%)","recoveries":24,"big_chances":0,"tackles_won":27,"total_saves":0,"total_shots":3,"aerial_duels":"2/2 (100%)","corner_kicks":0,"dispossessed":5,"ground_duels":"21/40 (53%)","hit_woodwork":0,"yellow_cards":0,"blocked_shots":1,"interceptions":5,"through_balls":0,"total_tackles":11,"accurate_passes":106,"ball_possession":31,"shots_on_target":2,"goalkeeper_saves":0,"shots_inside_box":2,"shots_off_target":0,"shots_outside_box":1,"big_chances_missed":0,"big_chances_scored":0,"final_third_entries":15,"fouled_in_final_third":1},"home":{"duels":45,"fouls":7,"passes":330,"crosses":"0/7 (0%)","tackles":10,"dribbles":"4/10 (40%)","offsides":0,"throw_ins":9,"clearances":9,"free_kicks":5,"goal_kicks":1,"long_balls":"6/13 (46%)","recoveries":33,"big_chances":1,"tackles_won":70,"total_saves":2,"total_shots":7,"aerial_duels":"1/3 (33%)","corner_kicks":4,"dispossessed":5,"ground_duels":"18/39 (46%)","hit_woodwork":2,"yellow_cards":0,"blocked_shots":3,"interceptions":5,"through_balls":1,"total_tackles":10,"accurate_passes":298,"ball_possession":69,"shots_on_target":1,"goalkeeper_saves":2,"shots_inside_box":4,"shots_off_target":3,"shots_outside_box":3,"big_chances_missed":0,"big_chances_scored":1,"final_third_entries":54,"fouled_in_final_third":2}},"second_half":{"away":{"duels":40,"fouls":6,"passes":140,"crosses":"3/5 (60%)","tackles":3,"dribbles":"0/5 (0%)","offsides":0,"throw_ins":9,"clearances":6,"free_kicks":6,"goal_kicks":6,"long_balls":"7/14 (50%)","recoveries":12,"big_chances":1,"tackles_won":67,"total_saves":1,"total_shots":8,"aerial_duels":"5/10 (50%)","corner_kicks":2,"dispossessed":3,"ground_duels":"9/25 (36%)","hit_woodwork":1,"yellow_cards":1,"blocked_shots":3,"interceptions":2,"through_balls":1,"total_tackles":3,"accurate_passes":113,"ball_possession":42,"shots_on_target":2,"goalkeeper_saves":1,"shots_inside_box":5,"shots_off_target":3,"shots_outside_box":3,"big_chances_missed":1,"big_chances_scored":0,"final_third_entries":16,"fouled_in_final_third":0},"home":{"duels":60,"fouls":6,"passes":191,"crosses":"3/6 (50%)","tackles":8,"dribbles":"2/3 (67%)","offsides":1,"throw_ins":7,"clearances":10,"free_kicks":6,"goal_kicks":3,"long_balls":"13/22 (59%)","recoveries":17,"big_chances":1,"tackles_won":50,"total_saves":2,"total_shots":6,"aerial_duels":"5/10 (50%)","corner_kicks":4,"dispossessed":2,"ground_duels":"16/25 (64%)","hit_woodwork":0,"yellow_cards":1,"blocked_shots":2,"interceptions":1,"through_balls":0,"total_tackles":8,"accurate_passes":161,"ball_possession":58,"shots_on_target":2,"goalkeeper_saves":2,"shots_inside_box":3,"shots_off_target":2,"shots_outside_box":3,"big_chances_missed":0,"big_chances_scored":1,"final_third_entries":23,"fouled_in_final_third":0}}}}]