[{"id":7709,"league":{"id":23,"name":"Superliga","country":"Romania","is_women":false,"current_season":{"id":374,"name":"Superliga 25/26","year":2025,"start_date":"2025-07-01","end_date":"2026-06-30"}},"home_team":"FC Universitatea Cluj","away_team":"FC Dinamo București","home_team_obj":{"id":355,"name":"FC Universitatea Cluj","short_name":"U. Cluj","country":"Romania","coach":{"name":"Cristiano Bergodi","shortName":"C. Bergodi"},"venue":{"id":335,"name":"Cluj Arena","city":"Cluj Napoca","country":"Romania","capacity":30246}},"away_team_obj":{"id":368,"name":"FC Dinamo București","short_name":"Dinamo București","country":"Romania","coach":{"name":"Željko Kopić","shortName":"Ž. Kopić"},"venue":{"id":348,"name":"Dinamo Stadium","city":"Bucharest","country":"Romania","capacity":15032}},"event_date":"2026-05-23T21:30:00+04:00","group_name":null,"status":"halftime","home_score":1,"away_score":0,"home_score_ht":1,"away_score_ht":0,"penalty_shootout":null,"extra_time_score":null,"current_minute":45,"period":"HT","home_xg_live":null,"away_xg_live":null,"incidents":[{"text":"HT","type":"period","minute":45,"is_live":false,"added_time":999,"away_score":0,"home_score":1},{"type":"injuryTime","length":1,"minute":45},{"type":"goal","assist":"J. Stanojev","minute":30,"player":"A. Gheorghiță","is_home":true,"sequence":[{"end":{"x":47.8,"y":13.9},"pid":1907275,"pos":{"x":42.7,"y":30.7},"event":"pass","player":"A. Trică"},{"end":{"x":81.1,"y":74.6},"pid":889106,"pos":{"x":47.8,"y":13.9},"event":"ball-movement","player":"J. Stanojev"},{"end":{"x":81.1,"y":74.6},"pid":889106,"pos":{"x":73.8,"y":64.4},"event":"pass","assist":true,"player":"J. Stanojev"},{"gk":{"x":98.5,"y":51.8},"gm":{"x":27.42,"y":93.67},"pid":1113174,"pos":{"x":86.2,"y":71},"body":"right-foot","event":"goal","player":"A. Gheorghiță"}],"goal_type":"regular","player_id":1113174,"added_time":null,"away_score":0,"home_score":1}],"live_stats":{"away":{"duels":67,"fouls":4,"passes":331,"crosses":"0/3 (0%)","tackles":6,"dribbles":"4/6 (67%)","offsides":0,"throw_ins":7,"clearances":6,"free_kicks":0,"goal_kicks":2,"long_balls":"8/24 (33%)","recoveries":30,"tackles_won":83,"total_saves":2,"total_shots":6,"aerial_duels":"10/11 (91%)","corner_kicks":1,"dispossessed":2,"ground_duels":"10/19 (53%)","hit_woodwork":1,"blocked_shots":3,"interceptions":4,"through_balls":0,"total_tackles":6,"accurate_passes":291,"ball_possession":54,"shots_on_target":1,"goalkeeper_saves":2,"shots_inside_box":4,"shots_off_target":2,"final_third_phase":"51/76 (67%)","shots_outside_box":2,"final_third_entries":24,"touches_in_penalty_area":6},"home":{"duels":33,"fouls":0,"passes":278,"crosses":"0/3 (0%)","tackles":4,"dribbles":"1/4 (25%)","offsides":1,"throw_ins":9,"clearances":7,"free_kicks":4,"goal_kicks":7,"long_balls":"15/33 (45%)","recoveries":29,"tackles_won":75,"total_saves":1,"total_shots":4,"aerial_duels":"1/11 (9%)","corner_kicks":2,"dispossessed":3,"ground_duels":"9/19 (47%)","hit_woodwork":0,"blocked_shots":0,"interceptions":3,"through_balls":1,"total_tackles":4,"accurate_passes":239,"ball_possession":46,"shots_on_target":3,"goalkeeper_saves":1,"shots_inside_box":2,"shots_off_target":1,"final_third_phase":"16/20 (80%)","shots_outside_box":2,"final_third_entries":7,"touches_in_penalty_area":3},"first_half":{"away":{"duels":67,"fouls":4,"passes":331,"crosses":"0/3 (0%)","tackles":6,"dribbles":"4/6 (67%)","offsides":0,"throw_ins":7,"clearances":6,"free_kicks":0,"goal_kicks":2,"long_balls":"8/24 (33%)","recoveries":30,"tackles_won":83,"total_saves":2,"total_shots":6,"aerial_duels":"10/11 (91%)","corner_kicks":1,"dispossessed":2,"ground_duels":"10/19 (53%)","hit_woodwork":1,"blocked_shots":3,"interceptions":4,"through_balls":0,"total_tackles":6,"accurate_passes":291,"ball_possession":54,"shots_on_target":1,"goalkeeper_saves":2,"shots_inside_box":4,"shots_off_target":2,"shots_outside_box":2,"final_third_entries":24},"home":{"duels":33,"fouls":0,"passes":278,"crosses":"0/3 (0%)","tackles":4,"dribbles":"1/4 (25%)","offsides":1,"throw_ins":9,"clearances":7,"free_kicks":4,"goal_kicks":7,"long_balls":"15/33 (45%)","recoveries":29,"tackles_won":75,"total_saves":1,"total_shots":4,"aerial_duels":"1/11 (9%)","corner_kicks":2,"dispossessed":3,"ground_duels":"9/19 (47%)","hit_woodwork":0,"blocked_shots":0,"interceptions":3,"through_balls":1,"total_tackles":4,"accurate_passes":239,"ball_possession":46,"shots_on_target":3,"goalkeeper_saves":1,"shots_inside_box":2,"shots_off_target":1,"shots_outside_box":2,"final_third_entries":7}}}},{"id":207477,"league":{"id":53,"name":"Botola Pro","country":"Morocco","is_women":false,"current_season":null},"home_team":"Wydad Casablanca","away_team":"Hassania d'Agadir","home_team_obj":{"id":2064,"name":"Wydad Casablanca","short_name":"WAC","country":"Morocco","coach":{"name":"Mohamed Benchrifa","shortName":"M. Benchrifa"},"venue":null},"away_team_obj":{"id":2060,"name":"Hassania d'Agadir","short_name":"HUSA","country":"Morocco","coach":{"name":"Hilal Et-Tair","shortName":"H. Et-Tair"},"venue":null},"event_date":"2026-05-23T22:00:00+04:00","group_name":null,"status":"1st_half","home_score":0,"away_score":0,"home_score_ht":null,"away_score_ht":null,"penalty_shootout":null,"extra_time_score":null,"current_minute":32,"period":"1T","home_xg_live":null,"away_xg_live":null,"incidents":[{"text":"First half","type":"period","minute":45,"is_live":true,"added_time":999,"away_score":0,"home_score":0},{"type":"substitution","minute":26,"is_home":false,"player_in":"H. Ahaddad","added_time":null,"player_out":"B. Ilou","player_in_id":1010890,"player_out_id":2003720}],"live_stats":null},{"id":205204,"league":{"id":43,"name":"DFB Pokal","country":"Germany","is_women":false,"current_season":null},"home_team":"FC Bayern München","away_team":"VfB Stuttgart","home_team_obj":{"id":79,"name":"FC Bayern München","short_name":"Bayern","country":"Germany","coach":{"name":"Vincent Kompany","shortName":"V. Kompany"},"venue":{"id":77,"name":"Allianz Arena","city":"Munich","country":"Germany","capacity":75024}},"away_team_obj":{"id":84,"name":"VfB Stuttgart","short_name":"Stuttgart","country":"Germany","coach":{"name":"Sebastian Hoeneß","shortName":"S. Hoeneß"},"venue":{"id":82,"name":"MHP Arena","city":"Stuttgart","country":"Germany","capacity":60449}},"event_date":"2026-05-23T22:00:00+04:00","group_name":null,"status":"1st_half","home_score":0,"away_score":0,"home_score_ht":null,"away_score_ht":null,"penalty_shootout":null,"extra_time_score":null,"current_minute":32,"period":"1T","home_xg_live":null,"away_xg_live":null,"incidents":[{"text":"First half","type":"period","minute":45,"is_live":true,"added_time":999,"away_score":0,"home_score":0}],"live_stats":{"away":{"duels":58,"fouls":4,"passes":121,"crosses":"3/7 (43%)","punches":1,"tackles":10,"dribbles":"0/2 (0%)","offsides":0,"big_saves":0,"throw_ins":4,"clearances":7,"free_kicks":1,"goal_kicks":3,"long_balls":"5/23 (22%)","recoveries":19,"tackles_won":50,"total_saves":1,"total_shots":7,"aerial_duels":"8/10 (80%)","corner_kicks":2,"dispossessed":3,"ground_duels":"11/23 (48%)","hit_woodwork":0,"blocked_shots":2,"interceptions":1,"total_tackles":10,"accurate_passes":82,"ball_possession":39,"shots_on_target":3,"goalkeeper_saves":1,"shots_inside_box":4,"shots_off_target":2,"final_third_phase":"23/38 (61%)","shots_outside_box":3,"final_third_entries":23,"errors_lead_to_a_shot":0,"touches_in_penalty_area":8},"home":{"duels":42,"fouls":1,"passes":201,"crosses":"1/2 (50%)","punches":0,"tackles":5,"dribbles":"3/7 (43%)","offsides":1,"big_saves":1,"throw_ins":4,"clearances":3,"free_kicks":4,"goal_kicks":3,"long_balls":"7/29 (24%)","recoveries":22,"tackles_won":60,"total_saves":3,"total_shots":1,"aerial_duels":"2/10 (20%)","corner_kicks":0,"dispossessed":6,"ground_duels":"12/23 (52%)","hit_woodwork":0,"blocked_shots":0,"interceptions":3,"total_tackles":5,"accurate_passes":156,"ball_possession":61,"shots_on_target":1,"goalkeeper_saves":3,"shots_inside_box":1,"shots_off_target":1,"final_third_phase":"10/23 (43%)","shots_outside_box":0,"final_third_entries":14,"errors_lead_to_a_shot":1,"touches_in_penalty_area":5},"first_half":{"away":{"duels":58,"fouls":4,"passes":121,"crosses":"3/7 (43%)","tackles":10,"dribbles":"0/2 (0%)","offsides":0,"throw_ins":4,"clearances":7,"free_kicks":1,"goal_kicks":3,"long_balls":"5/23 (22%)","recoveries":19,"tackles_won":50,"total_saves":1,"total_shots":7,"aerial_duels":"8/10 (80%)","corner_kicks":2,"dispossessed":3,"ground_duels":"11/23 (48%)","hit_woodwork":0,"blocked_shots":2,"interceptions":1,"total_tackles":10,"accurate_passes":82,"ball_possession":39,"shots_on_target":3,"goalkeeper_saves":1,"shots_inside_box":4,"shots_off_target":2,"shots_outside_box":3,"final_third_entries":23},"home":{"duels":42,"fouls":1,"passes":201,"crosses":"1/2 (50%)","tackles":5,"dribbles":"3/7 (43%)","offsides":1,"throw_ins":4,"clearances":3,"free_kicks":4,"goal_kicks":3,"long_balls":"7/29 (24%)","recoveries":22,"tackles_won":60,"total_saves":3,"total_shots":1,"aerial_duels":"2/10 (20%)","corner_kicks":0,"dispossessed":6,"ground_duels":"12/23 (52%)","hit_woodwork":0,"blocked_shots":0,"interceptions":3,"total_tackles":5,"accurate_passes":156,"ball_possession":61,"shots_on_target":1,"goalkeeper_saves":3,"shots_inside_box":1,"shots_off_target":1,"shots_outside_box":0,"final_third_entries":14}}}}]