[{"id":205761,"league":{"id":52,"name":"Chinese Super League","country":"China","is_women":false,"current_season":{"id":1040,"name":"Chinese Super League 2026","year":2026,"start_date":"2026-01-01","end_date":"2026-12-31"}},"home_team":"Wuhan Three Towns","away_team":"Qingdao Hainiu","home_team_obj":{"id":2043,"name":"Wuhan Three Towns","short_name":"Three Towns","country":"China","coach":{"name":"Benjamin Mora","shortName":"B. Mora"},"venue":null},"away_team_obj":{"id":2040,"name":"Qingdao Hainiu","short_name":"Hainiu","country":"China","coach":{"name":"Milan Ristic","shortName":"M. Ristic"},"venue":null},"event_date":"2026-05-06T15:00:00+04:00","group_name":null,"status":"2nd_half","home_score":0,"away_score":1,"home_score_ht":0,"away_score_ht":1,"penalty_shootout":null,"extra_time_score":null,"current_minute":51,"period":"2T","home_xg_live":null,"away_xg_live":null,"incidents":[{"text":"Second half","type":"period","minute":90,"is_live":true,"added_time":999,"away_score":1,"home_score":0},{"type":"substitution","minute":46,"is_home":true,"player_in":"X. Xia","added_time":null,"player_out":"L. Jiang","player_in_id":2114611,"player_out_id":2115489},{"type":"substitution","minute":46,"is_home":true,"player_in":"M. Tian","added_time":null,"player_out":"Z. Chen","player_in_id":840941,"player_out_id":828228},{"text":"HT","type":"period","minute":45,"is_live":false,"added_time":999,"away_score":1,"home_score":0},{"type":"goal","assist":"Y. Yeboah","minute":45,"player":"J. Yonghao","is_home":false,"sequence":[{"end":{"x":30.9,"y":82.7},"pid":333423,"pos":{"x":26.1,"y":73.9},"event":"pass","player":"C. Strandberg"},{"end":{"x":30.2,"y":65},"pid":796323,"pos":{"x":30.9,"y":82.7},"event":"pass","player":"Y. Yeboah"},{"end":{"x":34.9,"y":77.3},"pid":914694,"pos":{"x":30.5,"y":66.3},"event":"pass","player":"M. Edjouma"},{"end":{"x":9.3,"y":82.2},"pid":797580,"pos":{"x":34.9,"y":77.3},"event":"pass","player":"C. Lin"},{"end":{"x":9.6,"y":54.5},"pid":796323,"pos":{"x":9.3,"y":82.2},"event":"cross","assist":true,"player":"Y. Yeboah"},{"gk":{"x":2.2,"y":51.3},"gm":{"x":61.29,"y":47.33},"pid":1428989,"pos":{"x":9.6,"y":54.5},"body":"right-foot","event":"goal","player":"J. Yonghao"}],"goal_type":"regular","player_id":1428989,"added_time":4,"away_score":1,"home_score":0},{"type":"injuryTime","length":7,"minute":45},{"type":"varDecision","minute":41,"player":"N. Anđelković","is_home":false,"decision":"penaltyNotAwarded","confirmed":true,"player_id":881538}],"live_stats":{"away":{"duels":61,"fouls":7,"passes":197,"crosses":"4/11 (36%)","tackles":13,"dribbles":"5/8 (63%)","offsides":0,"throw_ins":7,"clearances":13,"free_kicks":7,"goal_kicks":2,"long_balls":"18/37 (49%)","recoveries":23,"big_chances":1,"high_claims":1,"tackles_won":23,"total_saves":0,"total_shots":9,"aerial_duels":"10/17 (59%)","corner_kicks":7,"dispossessed":3,"ground_duels":"25/40 (63%)","hit_woodwork":0,"blocked_shots":4,"interceptions":5,"total_tackles":13,"accurate_passes":160,"ball_possession":55,"shots_on_target":2,"goalkeeper_saves":0,"shots_inside_box":5,"shots_off_target":3,"final_third_phase":"41/56 (73%)","shots_outside_box":4,"big_chances_scored":1,"final_third_entries":32,"fouled_in_final_third":2,"touches_in_penalty_area":8},"home":{"duels":39,"fouls":7,"passes":161,"crosses":"1/6 (17%)","tackles":6,"dribbles":"2/11 (18%)","offsides":2,"throw_ins":15,"clearances":10,"free_kicks":7,"goal_kicks":6,"long_balls":"17/27 (63%)","recoveries":14,"big_chances":0,"high_claims":0,"tackles_won":83,"total_saves":1,"total_shots":1,"aerial_duels":"7/17 (41%)","corner_kicks":3,"dispossessed":4,"ground_duels":"15/40 (38%)","hit_woodwork":0,"blocked_shots":0,"interceptions":1,"total_tackles":6,"accurate_passes":124,"ball_possession":45,"shots_on_target":0,"goalkeeper_saves":1,"shots_inside_box":0,"shots_off_target":1,"final_third_phase":"21/41 (51%)","shots_outside_box":1,"big_chances_scored":0,"final_third_entries":26,"fouled_in_final_third":1,"touches_in_penalty_area":6},"first_half":{"away":{"duels":65,"fouls":5,"passes":179,"crosses":"4/11 (36%)","tackles":13,"dribbles":"5/7 (71%)","offsides":0,"throw_ins":6,"clearances":13,"free_kicks":7,"goal_kicks":2,"long_balls":"17/32 (53%)","recoveries":21,"big_chances":1,"tackles_won":23,"total_saves":0,"total_shots":9,"aerial_duels":"9/15 (60%)","corner_kicks":7,"dispossessed":3,"ground_duels":"25/37 (68%)","hit_woodwork":0,"blocked_shots":4,"interceptions":5,"total_tackles":13,"accurate_passes":146,"ball_possession":55,"shots_on_target":2,"goalkeeper_saves":0,"shots_inside_box":5,"shots_off_target":3,"shots_outside_box":4,"big_chances_scored":1,"final_third_entries":26,"fouled_in_final_third":2},"home":{"duels":35,"fouls":7,"passes":148,"crosses":"1/6 (17%)","tackles":5,"dribbles":"2/11 (18%)","offsides":1,"throw_ins":13,"clearances":8,"free_kicks":5,"goal_kicks":6,"long_balls":"15/24 (63%)","recoveries":14,"big_chances":0,"tackles_won":80,"total_saves":1,"total_shots":1,"aerial_duels":"6/15 (40%)","corner_kicks":3,"dispossessed":4,"ground_duels":"12/37 (32%)","hit_woodwork":0,"blocked_shots":0,"interceptions":1,"total_tackles":5,"accurate_passes":114,"ball_possession":45,"shots_on_target":0,"goalkeeper_saves":1,"shots_inside_box":0,"shots_off_target":1,"shots_outside_box":1,"big_chances_scored":0,"final_third_entries":25,"fouled_in_final_third":1}},"second_half":{"away":{"duels":20,"fouls":2,"passes":18,"crosses":"0/0 (0%)","tackles":0,"dribbles":"0/1 (0%)","offsides":0,"throw_ins":1,"clearances":0,"free_kicks":0,"goal_kicks":0,"long_balls":"1/5 (20%)","recoveries":2,"big_chances":0,"tackles_won":0,"total_saves":0,"total_shots":0,"aerial_duels":"1/2 (50%)","corner_kicks":0,"dispossessed":0,"ground_duels":"0/3 (0%)","hit_woodwork":0,"blocked_shots":0,"interceptions":0,"total_tackles":0,"accurate_passes":14,"ball_possession":58,"shots_on_target":0,"goalkeeper_saves":0,"shots_inside_box":0,"shots_off_target":0,"shots_outside_box":0,"big_chances_scored":0,"final_third_entries":6,"fouled_in_final_third":0},"home":{"duels":80,"fouls":0,"passes":13,"crosses":"0/0 (0%)","tackles":1,"dribbles":"0/0 (0%)","offsides":1,"throw_ins":2,"clearances":2,"free_kicks":2,"goal_kicks":0,"long_balls":"2/3 (67%)","recoveries":0,"big_chances":0,"tackles_won":100,"total_saves":0,"total_shots":0,"aerial_duels":"1/2 (50%)","corner_kicks":0,"dispossessed":0,"ground_duels":"3/3 (100%)","hit_woodwork":0,"blocked_shots":0,"interceptions":0,"total_tackles":1,"accurate_passes":10,"ball_possession":42,"shots_on_target":0,"goalkeeper_saves":0,"shots_inside_box":0,"shots_off_target":0,"shots_outside_box":0,"big_chances_scored":0,"final_third_entries":1,"fouled_in_final_third":0}}}},{"id":205762,"league":{"id":52,"name":"Chinese Super League","country":"China","is_women":false,"current_season":{"id":1040,"name":"Chinese Super League 2026","year":2026,"start_date":"2026-01-01","end_date":"2026-12-31"}},"home_team":"Beijing Guoan","away_team":"Dalian Yingbo FC","home_team_obj":{"id":2044,"name":"Beijing Guoan","short_name":"Guoan","country":"China","coach":{"name":"Nick Montgomery","shortName":"N. Montgomery"},"venue":null},"away_team_obj":{"id":2036,"name":"Dalian Yingbo FC","short_name":"Dalian Yingbo","country":"China","coach":{"name":"Guoxu Li","shortName":"G. Li"},"venue":null},"event_date":"2026-05-06T15:35:00+04:00","group_name":null,"status":"1st_half","home_score":0,"away_score":0,"home_score_ht":null,"away_score_ht":null,"penalty_shootout":null,"extra_time_score":null,"current_minute":39,"period":"1T","home_xg_live":null,"away_xg_live":null,"incidents":[{"text":"First half","type":"period","minute":45,"is_live":true,"added_time":999,"away_score":0,"home_score":0},{"type":"card","minute":13,"player":"Y. Mingrui","is_home":false,"card_type":"yellow","player_id":1501548,"added_time":null},{"type":"card","minute":6,"player":"M. Weijie","is_home":false,"card_type":"yellow","player_id":2038795,"added_time":null}],"live_stats":{"away":{"duels":37,"fouls":10,"passes":88,"crosses":"0/3 (0%)","tackles":5,"dribbles":"0/0 (0%)","offsides":0,"throw_ins":3,"clearances":10,"free_kicks":6,"goal_kicks":3,"long_balls":"8/26 (31%)","recoveries":16,"big_chances":0,"tackles_won":80,"total_saves":2,"total_shots":1,"aerial_duels":"2/4 (50%)","corner_kicks":0,"dispossessed":3,"ground_duels":"10/28 (36%)","hit_woodwork":0,"yellow_cards":2,"blocked_shots":0,"interceptions":5,"total_tackles":5,"accurate_passes":52,"ball_possession":22,"shots_on_target":1,"goalkeeper_saves":2,"shots_inside_box":1,"shots_off_target":0,"final_third_phase":"9/23 (39%)","shots_outside_box":0,"big_chances_missed":0,"final_third_entries":20,"fouled_in_final_third":0,"touches_in_penalty_area":1},"home":{"duels":63,"fouls":6,"passes":311,"crosses":"3/8 (38%)","tackles":3,"dribbles":"5/8 (63%)","offsides":2,"throw_ins":9,"clearances":5,"free_kicks":10,"goal_kicks":0,"long_balls":"4/7 (57%)","recoveries":21,"big_chances":1,"tackles_won":100,"total_saves":1,"total_shots":7,"aerial_duels":"2/4 (50%)","corner_kicks":1,"dispossessed":2,"ground_duels":"18/28 (64%)","hit_woodwork":0,"yellow_cards":0,"blocked_shots":2,"interceptions":3,"total_tackles":3,"accurate_passes":283,"ball_possession":78,"shots_on_target":2,"goalkeeper_saves":1,"shots_inside_box":6,"shots_off_target":3,"final_third_phase":"55/75 (73%)","shots_outside_box":1,"big_chances_missed":1,"final_third_entries":35,"fouled_in_final_third":1,"touches_in_penalty_area":9},"first_half":{"away":{"duels":37,"fouls":10,"passes":88,"crosses":"0/3 (0%)","tackles":5,"dribbles":"0/0 (0%)","offsides":0,"throw_ins":3,"clearances":10,"free_kicks":6,"goal_kicks":3,"long_balls":"8/26 (31%)","recoveries":16,"big_chances":0,"tackles_won":80,"total_saves":2,"total_shots":1,"aerial_duels":"2/4 (50%)","corner_kicks":0,"dispossessed":3,"ground_duels":"10/28 (36%)","hit_woodwork":0,"yellow_cards":2,"blocked_shots":0,"interceptions":5,"total_tackles":5,"accurate_passes":52,"ball_possession":22,"shots_on_target":1,"goalkeeper_saves":2,"shots_inside_box":1,"shots_off_target":0,"shots_outside_box":0,"big_chances_missed":0,"final_third_entries":20,"fouled_in_final_third":0},"home":{"duels":63,"fouls":6,"passes":311,"crosses":"3/8 (38%)","tackles":3,"dribbles":"5/8 (63%)","offsides":2,"throw_ins":9,"clearances":5,"free_kicks":10,"goal_kicks":0,"long_balls":"4/7 (57%)","recoveries":21,"big_chances":1,"tackles_won":100,"total_saves":1,"total_shots":7,"aerial_duels":"2/4 (50%)","corner_kicks":1,"dispossessed":2,"ground_duels":"18/28 (64%)","hit_woodwork":0,"yellow_cards":0,"blocked_shots":2,"interceptions":3,"total_tackles":3,"accurate_passes":283,"ball_possession":78,"shots_on_target":2,"goalkeeper_saves":1,"shots_inside_box":6,"shots_off_target":3,"shots_outside_box":1,"big_chances_missed":1,"final_third_entries":35,"fouled_in_final_third":1}}}},{"id":205763,"league":{"id":52,"name":"Chinese Super League","country":"China","is_women":false,"current_season":{"id":1040,"name":"Chinese Super League 2026","year":2026,"start_date":"2026-01-01","end_date":"2026-12-31"}},"home_team":"Shanghai Port","away_team":"Shenzhen Peng City","home_team_obj":{"id":2037,"name":"Shanghai Port","short_name":"Port","country":"China","coach":{"name":"Kevin Muscat","shortName":"K. Muscat"},"venue":null},"away_team_obj":{"id":2030,"name":"Shenzhen Peng City","short_name":"Shenzhen","country":"China","coach":{"name":"Chen Tao","shortName":"C. Tao"},"venue":null},"event_date":"2026-05-06T15:35:00+04:00","group_name":null,"status":"1st_half","home_score":0,"away_score":0,"home_score_ht":null,"away_score_ht":null,"penalty_shootout":null,"extra_time_score":null,"current_minute":39,"period":"1T","home_xg_live":null,"away_xg_live":null,"incidents":[{"text":"First half","type":"period","minute":45,"is_live":true,"added_time":999,"away_score":0,"home_score":0},{"type":"substitution","minute":30,"is_home":true,"player_in":"Z. Linpeng","added_time":null,"player_out":"W. Shenchao","player_in_id":137746,"player_out_id":797337},{"type":"substitution","minute":14,"is_home":false,"player_in":"Y. Yang","added_time":null,"player_out":"F. Benković","player_in_id":840582,"player_out_id":357588}],"live_stats":{"away":{"duels":52,"fouls":4,"passes":118,"crosses":"0/3 (0%)","tackles":3,"dribbles":"0/4 (0%)","offsides":1,"throw_ins":10,"clearances":15,"free_kicks":7,"goal_kicks":8,"long_balls":"6/27 (22%)","recoveries":12,"tackles_won":33,"total_shots":1,"aerial_duels":"6/10 (60%)","corner_kicks":0,"dispossessed":1,"ground_duels":"10/21 (48%)","hit_woodwork":0,"blocked_shots":0,"interceptions":2,"total_tackles":3,"accurate_passes":77,"ball_possession":39,"shots_on_target":0,"shots_inside_box":0,"shots_off_target":1,"final_third_phase":"9/25 (36%)","shots_outside_box":1,"final_third_entries":20,"fouled_in_final_third":1,"touches_in_penalty_area":0},"home":{"duels":48,"fouls":7,"passes":170,"crosses":"4/15 (27%)","tackles":5,"dribbles":"2/3 (67%)","offsides":1,"throw_ins":13,"clearances":7,"free_kicks":4,"goal_kicks":3,"long_balls":"9/15 (60%)","recoveries":15,"tackles_won":60,"total_shots":4,"aerial_duels":"4/10 (40%)","corner_kicks":1,"dispossessed":2,"ground_duels":"11/21 (52%)","hit_woodwork":0,"blocked_shots":1,"interceptions":3,"total_tackles":5,"accurate_passes":147,"ball_possession":61,"shots_on_target":0,"shots_inside_box":3,"shots_off_target":3,"final_third_phase":"40/51 (78%)","shots_outside_box":1,"final_third_entries":21,"fouled_in_final_third":2,"touches_in_penalty_area":9},"first_half":{"away":{"duels":52,"fouls":4,"passes":118,"crosses":"0/3 (0%)","tackles":3,"dribbles":"0/4 (0%)","offsides":1,"throw_ins":10,"clearances":15,"free_kicks":7,"goal_kicks":8,"long_balls":"6/27 (22%)","recoveries":12,"tackles_won":33,"total_shots":1,"aerial_duels":"6/10 (60%)","corner_kicks":0,"dispossessed":1,"ground_duels":"10/21 (48%)","hit_woodwork":0,"blocked_shots":0,"interceptions":2,"total_tackles":3,"accurate_passes":77,"ball_possession":39,"shots_on_target":0,"shots_inside_box":0,"shots_off_target":1,"shots_outside_box":1,"final_third_entries":20,"fouled_in_final_third":1},"home":{"duels":48,"fouls":7,"passes":170,"crosses":"4/15 (27%)","tackles":5,"dribbles":"2/3 (67%)","offsides":1,"throw_ins":13,"clearances":7,"free_kicks":4,"goal_kicks":3,"long_balls":"9/15 (60%)","recoveries":15,"tackles_won":60,"total_shots":4,"aerial_duels":"4/10 (40%)","corner_kicks":1,"dispossessed":2,"ground_duels":"11/21 (52%)","hit_woodwork":0,"blocked_shots":1,"interceptions":3,"total_tackles":5,"accurate_passes":147,"ball_possession":61,"shots_on_target":0,"shots_inside_box":3,"shots_off_target":3,"shots_outside_box":1,"final_third_entries":21,"fouled_in_final_third":2}}}},{"id":205764,"league":{"id":52,"name":"Chinese Super League","country":"China","is_women":false,"current_season":{"id":1040,"name":"Chinese Super League 2026","year":2026,"start_date":"2026-01-01","end_date":"2026-12-31"}},"home_team":"Yunnan Yukun","away_team":"Zhejiang","home_team_obj":{"id":2039,"name":"Yunnan Yukun","short_name":"Yukun","country":"China","coach":{"name":"Jordi Vinyals","shortName":"J. Vinyals"},"venue":null},"away_team_obj":{"id":2041,"name":"Zhejiang","short_name":"Zhejiang","country":"China","coach":{"name":"Ross Aloisi","shortName":"R. Aloisi"},"venue":null},"event_date":"2026-05-06T16:00:00+04:00","group_name":null,"status":"1st_half","home_score":1,"away_score":0,"home_score_ht":null,"away_score_ht":null,"penalty_shootout":null,"extra_time_score":null,"current_minute":13,"period":"1T","home_xg_live":null,"away_xg_live":null,"incidents":[{"text":"First half","type":"period","minute":45,"is_live":true,"added_time":999,"away_score":0,"home_score":1},{"type":"card","minute":12,"player":"M. Tolić","is_home":false,"card_type":"yellow","player_id":784673,"added_time":null},{"type":"goal","assist":"O. T. Maritu","minute":6,"player":"Cléber","is_home":true,"sequence":[{"pid":792267,"pos":{"x":45.5,"y":12.2},"event":"ball-touch","player":"C. Ye"},{"end":{"x":56.6,"y":30.3},"pid":828225,"pos":{"x":42.8,"y":24.9},"event":"pass","player":"K. Shi"},{"end":{"x":45.8,"y":38.8},"pid":553646,"pos":{"x":56.6,"y":30.3},"event":"pass","player":"J. H. Sæter"},{"end":{"x":95,"y":61.4},"pid":828226,"pos":{"x":45.8,"y":38.8},"event":"ball-movement","player":"X. Xu"},{"end":{"x":95,"y":61.4},"pid":828226,"pos":{"x":66.2,"y":18.2},"event":"cross","player":"X. Xu"},{"end":{"x":96.1,"y":42.1},"pid":941696,"pos":{"x":95,"y":61.4},"event":"pass","assist":true,"player":"O. T. Maritu"},{"gk":{"x":99.4,"y":48.6},"gm":{"x":58.6,"y":73.67},"pid":975207,"pos":{"x":96.1,"y":42.1},"body":"head","event":"goal","player":"Cléber"}],"goal_type":"regular","player_id":975207,"added_time":null,"away_score":0,"home_score":1}],"live_stats":{"away":{"duels":37,"fouls":2,"passes":44,"crosses":"0/0 (0%)","tackles":1,"dribbles":"0/0 (0%)","throw_ins":3,"clearances":1,"free_kicks":2,"goal_kicks":2,"long_balls":"1/7 (14%)","recoveries":3,"big_chances":0,"tackles_won":100,"total_shots":0,"aerial_duels":"0/3 (0%)","ground_duels":"3/5 (60%)","hit_woodwork":0,"yellow_cards":1,"blocked_shots":0,"interceptions":2,"total_tackles":1,"accurate_passes":34,"ball_possession":35,"shots_on_target":0,"shots_inside_box":0,"shots_off_target":0,"final_third_phase":"0/6 (0%)","shots_outside_box":0,"big_chances_missed":0,"big_chances_scored":0,"final_third_entries":6,"touches_in_penalty_area":0},"home":{"duels":63,"fouls":2,"passes":80,"crosses":"1/1 (100%)","tackles":0,"dribbles":"0/1 (0%)","throw_ins":3,"clearances":2,"free_kicks":2,"goal_kicks":2,"long_balls":"4/8 (50%)","recoveries":4,"big_chances":2,"tackles_won":0,"total_shots":2,"aerial_duels":"3/3 (100%)","ground_duels":"2/5 (40%)","hit_woodwork":0,"yellow_cards":0,"blocked_shots":0,"interceptions":2,"total_tackles":0,"accurate_passes":70,"ball_possession":65,"shots_on_target":1,"shots_inside_box":2,"shots_off_target":1,"final_third_phase":"4/9 (44%)","shots_outside_box":0,"big_chances_missed":1,"big_chances_scored":1,"final_third_entries":6,"touches_in_penalty_area":3},"first_half":{"away":{"duels":37,"fouls":2,"passes":44,"crosses":"0/0 (0%)","tackles":1,"dribbles":"0/0 (0%)","throw_ins":3,"clearances":1,"free_kicks":2,"goal_kicks":2,"long_balls":"1/7 (14%)","recoveries":3,"big_chances":0,"tackles_won":100,"total_shots":0,"aerial_duels":"0/3 (0%)","ground_duels":"3/5 (60%)","hit_woodwork":0,"yellow_cards":1,"blocked_shots":0,"interceptions":2,"total_tackles":1,"accurate_passes":34,"ball_possession":35,"shots_on_target":0,"shots_inside_box":0,"shots_off_target":0,"shots_outside_box":0,"big_chances_missed":0,"big_chances_scored":0,"final_third_entries":6},"home":{"duels":63,"fouls":2,"passes":80,"crosses":"1/1 (100%)","tackles":0,"dribbles":"0/1 (0%)","throw_ins":3,"clearances":2,"free_kicks":2,"goal_kicks":2,"long_balls":"4/8 (50%)","recoveries":4,"big_chances":2,"tackles_won":0,"total_shots":2,"aerial_duels":"3/3 (100%)","ground_duels":"2/5 (40%)","hit_woodwork":0,"yellow_cards":0,"blocked_shots":0,"interceptions":2,"total_tackles":0,"accurate_passes":70,"ball_possession":65,"shots_on_target":1,"shots_inside_box":2,"shots_off_target":1,"shots_outside_box":0,"big_chances_missed":1,"big_chances_scored":1,"final_third_entries":6}}}}]