[{"id":10011,"league":{"id":34,"name":"Brasileirão Serie B","country":"Brazil","is_women":false,"current_season":{"id":52,"name":"Brasileiro Serie B 2026","year":2026,"start_date":"2026-01-01","end_date":"2026-12-31"}},"home_team":"Londrina","away_team":"Clube De Regatas Brasil","home_team_obj":{"id":821,"name":"Londrina","short_name":"Londrina","country":"Brazil","coach":{"name":"Rogério Micale","shortName":"R. Micale"},"venue":{"id":614,"name":"Estádio Jacy Scaff","city":"Londrina","country":"Brazil","capacity":36056}},"away_team_obj":{"id":831,"name":"Clube De Regatas Brasil","short_name":"CRB","country":"Brazil","coach":{"name":"Eduardo Barroca","shortName":"E. Barroca"},"venue":{"id":624,"name":"Estádio Rei Pelé","city":"Maceio","country":"Brazil","capacity":20800}},"event_date":"2026-07-04T23:00:00+04:00","group_name":null,"status":"1st_half","home_score":0,"away_score":0,"home_score_ht":null,"away_score_ht":null,"penalty_shootout":null,"extra_time_score":null,"current_minute":15,"period":"1T","home_xg_live":null,"away_xg_live":0.23,"incidents":[{"text":"First half","type":"period","minute":45,"is_live":true,"added_time":999,"away_score":0,"home_score":0},{"type":"varDecision","minute":14,"player":"","is_home":true,"decision":"vip_for_unknown","confirmed":true,"player_id":null,"added_time":null},{"type":"card","minute":12,"player":"Danielzinho","is_home":false,"card_type":"yellow","player_id":840218,"added_time":null}],"live_stats":{"away":{"duels":31,"fouls":2,"passes":34,"crosses":"1/3 (33%)","tackles":2,"dribbles":"1/1 (100%)","throw_ins":1,"clearances":4,"free_kicks":0,"goal_kicks":3,"long_balls":"3/6 (50%)","recoveries":3,"big_chances":1,"tackles_won":100,"total_shots":1,"aerial_duels":"1/5 (20%)","corner_kicks":1,"ground_duels":"3/8 (38%)","hit_woodwork":0,"yellow_cards":1,"blocked_shots":0,"interceptions":1,"total_tackles":2,"expected_goals":0.23,"accurate_passes":30,"ball_possession":44,"shots_on_target":0,"shots_inside_box":1,"shots_off_target":1,"final_third_phase":"2/6 (33%)","shots_outside_box":0,"big_chances_missed":1,"final_third_entries":6,"fouled_in_final_third":0,"touches_in_penalty_area":1},"home":{"duels":69,"fouls":0,"passes":38,"crosses":"3/8 (38%)","tackles":0,"dribbles":"3/5 (60%)","throw_ins":4,"clearances":5,"free_kicks":2,"goal_kicks":1,"long_balls":"1/4 (25%)","recoveries":3,"big_chances":0,"tackles_won":0,"total_shots":0,"aerial_duels":"4/5 (80%)","corner_kicks":2,"ground_duels":"5/8 (63%)","hit_woodwork":0,"yellow_cards":0,"blocked_shots":0,"interceptions":1,"total_tackles":0,"expected_goals":0.0,"accurate_passes":32,"ball_possession":56,"shots_on_target":0,"shots_inside_box":0,"shots_off_target":0,"final_third_phase":"8/10 (80%)","shots_outside_box":0,"big_chances_missed":0,"final_third_entries":6,"fouled_in_final_third":1,"touches_in_penalty_area":2},"first_half":{"away":{"duels":31,"fouls":2,"passes":34,"crosses":"1/3 (33%)","tackles":2,"dribbles":"1/1 (100%)","throw_ins":1,"clearances":4,"free_kicks":0,"goal_kicks":3,"long_balls":"3/6 (50%)","recoveries":3,"big_chances":1,"tackles_won":100,"total_shots":1,"aerial_duels":"1/5 (20%)","corner_kicks":1,"ground_duels":"3/8 (38%)","hit_woodwork":0,"yellow_cards":1,"blocked_shots":0,"interceptions":1,"total_tackles":2,"expected_goals":0.23,"accurate_passes":30,"ball_possession":44,"shots_on_target":0,"shots_inside_box":1,"shots_off_target":1,"shots_outside_box":0,"big_chances_missed":1,"final_third_entries":6,"fouled_in_final_third":0},"home":{"duels":69,"fouls":0,"passes":38,"crosses":"3/8 (38%)","tackles":0,"dribbles":"3/5 (60%)","throw_ins":4,"clearances":5,"free_kicks":2,"goal_kicks":1,"long_balls":"1/4 (25%)","recoveries":3,"big_chances":0,"tackles_won":0,"total_shots":0,"aerial_duels":"4/5 (80%)","corner_kicks":2,"ground_duels":"5/8 (63%)","hit_woodwork":0,"yellow_cards":0,"blocked_shots":0,"interceptions":1,"total_tackles":0,"expected_goals":0.0,"accurate_passes":32,"ball_possession":56,"shots_on_target":0,"shots_inside_box":0,"shots_off_target":0,"shots_outside_box":0,"big_chances_missed":0,"final_third_entries":6,"fouled_in_final_third":1}}}},{"id":10006,"league":{"id":34,"name":"Brasileirão Serie B","country":"Brazil","is_women":false,"current_season":{"id":52,"name":"Brasileiro Serie B 2026","year":2026,"start_date":"2026-01-01","end_date":"2026-12-31"}},"home_team":"Criciúma","away_team":"Sport Recife","home_team_obj":{"id":929,"name":"Criciúma","short_name":"Criciúma","country":"Brazil","coach":{"name":"Eduardo Baptista","shortName":"E. Baptista"},"venue":{"id":709,"name":"Estádio Heriberto Hülse","city":"Criciúma","country":"Brazil","capacity":19225}},"away_team_obj":{"id":159,"name":"Sport Recife","short_name":"Sport Recife","country":"Brazil","coach":{"name":"Gilmar Dal Pozzo","shortName":"G. D. Pozzo"},"venue":{"id":157,"name":"Ilha do Retiro","city":"Recife","country":"Brazil","capacity":27500}},"event_date":"2026-07-04T23:00:00+04:00","group_name":null,"status":"1st_half","home_score":0,"away_score":0,"home_score_ht":null,"away_score_ht":null,"penalty_shootout":null,"extra_time_score":null,"current_minute":10,"period":"1T","home_xg_live":0.03,"away_xg_live":0.02,"incidents":[{"text":"First half","type":"period","minute":45,"is_live":true,"added_time":999,"away_score":0,"home_score":0},{"type":"card","minute":3,"player":"T. R. S. Modesto","is_home":true,"card_type":"yellow","player_id":1636364,"added_time":null}],"live_stats":{"away":{"duels":60,"fouls":0,"passes":25,"crosses":"1/2 (50%)","offsides":0,"throw_ins":5,"clearances":1,"free_kicks":1,"goal_kicks":0,"long_balls":"0/5 (0%)","recoveries":3,"total_saves":1,"total_shots":2,"aerial_duels":"2/4 (50%)","ground_duels":"1/1 (100%)","hit_woodwork":0,"yellow_cards":0,"blocked_shots":1,"interceptions":1,"expected_goals":0.02,"accurate_passes":13,"ball_possession":41,"goals_prevented":0.04,"shots_on_target":0,"goalkeeper_saves":1,"shots_inside_box":1,"shots_off_target":1,"final_third_phase":"3/10 (30%)","shots_outside_box":1,"final_third_entries":8,"fouled_in_final_third":1,"touches_in_penalty_area":4},"home":{"duels":40,"fouls":1,"passes":37,"crosses":"0/2 (0%)","offsides":1,"throw_ins":0,"clearances":8,"free_kicks":0,"goal_kicks":2,"long_balls":"3/6 (50%)","recoveries":3,"total_saves":0,"total_shots":2,"aerial_duels":"2/4 (50%)","ground_duels":"0/1 (0%)","hit_woodwork":0,"yellow_cards":1,"blocked_shots":1,"interceptions":0,"expected_goals":0.03,"accurate_passes":28,"ball_possession":59,"goals_prevented":0.0,"shots_on_target":1,"goalkeeper_saves":0,"shots_inside_box":0,"shots_off_target":0,"final_third_phase":"4/5 (80%)","shots_outside_box":2,"final_third_entries":5,"fouled_in_final_third":0,"touches_in_penalty_area":0},"first_half":{"away":{"duels":60,"fouls":0,"passes":25,"crosses":"1/2 (50%)","offsides":0,"throw_ins":5,"clearances":1,"free_kicks":1,"goal_kicks":0,"long_balls":"0/5 (0%)","recoveries":3,"total_saves":1,"total_shots":2,"aerial_duels":"2/4 (50%)","ground_duels":"1/1 (100%)","hit_woodwork":0,"yellow_cards":0,"blocked_shots":1,"interceptions":1,"expected_goals":0.02,"accurate_passes":13,"ball_possession":41,"shots_on_target":0,"goalkeeper_saves":1,"shots_inside_box":1,"shots_off_target":1,"shots_outside_box":1,"final_third_entries":8,"fouled_in_final_third":1},"home":{"duels":40,"fouls":1,"passes":37,"crosses":"0/2 (0%)","offsides":1,"throw_ins":0,"clearances":8,"free_kicks":0,"goal_kicks":2,"long_balls":"3/6 (50%)","recoveries":3,"total_saves":0,"total_shots":2,"aerial_duels":"2/4 (50%)","ground_duels":"0/1 (0%)","hit_woodwork":0,"yellow_cards":1,"blocked_shots":1,"interceptions":0,"expected_goals":0.03,"accurate_passes":28,"ball_possession":59,"shots_on_target":1,"goalkeeper_saves":0,"shots_inside_box":0,"shots_off_target":0,"shots_outside_box":2,"final_third_entries":5,"fouled_in_final_third":0}}}},{"id":10010,"league":{"id":34,"name":"Brasileirão Serie B","country":"Brazil","is_women":false,"current_season":{"id":52,"name":"Brasileiro Serie B 2026","year":2026,"start_date":"2026-01-01","end_date":"2026-12-31"}},"home_team":"Grêmio Novorizontino","away_team":"Atlético Goianiense","home_team_obj":{"id":836,"name":"Grêmio Novorizontino","short_name":"Novorizontino","country":"Brazil","coach":{"name":"Enderson Moreira","shortName":"E. Moreira"},"venue":{"id":628,"name":"Estádio Dr. Jorge Ismael de Biasi","city":"Novo Horizonte","country":"Brazil","capacity":14096}},"away_team_obj":{"id":819,"name":"Atlético Goianiense","short_name":"Atlético-GO","country":"Brazil","coach":{"name":"Renan Brito","shortName":"R. Brito"},"venue":{"id":612,"name":"Estádio Antônio Accioly","city":"Goiânia","country":"Brazil","capacity":12500}},"event_date":"2026-07-04T23:00:00+04:00","group_name":null,"status":"1st_half","home_score":0,"away_score":0,"home_score_ht":null,"away_score_ht":null,"penalty_shootout":null,"extra_time_score":null,"current_minute":15,"period":"1T","home_xg_live":null,"away_xg_live":0.16,"incidents":[{"text":"First half","type":"period","minute":45,"is_live":true,"added_time":999,"away_score":0,"home_score":0}],"live_stats":{"away":{"duels":40,"fouls":3,"passes":68,"crosses":"1/3 (33%)","tackles":2,"dribbles":"0/1 (0%)","throw_ins":4,"clearances":5,"free_kicks":2,"goal_kicks":1,"long_balls":"9/14 (64%)","recoveries":9,"tackles_won":100,"total_shots":2,"aerial_duels":"1/3 (33%)","dispossessed":2,"ground_duels":"5/12 (42%)","hit_woodwork":0,"blocked_shots":2,"total_tackles":2,"expected_goals":0.16,"accurate_passes":57,"ball_possession":58,"shots_on_target":0,"shots_inside_box":2,"shots_off_target":0,"final_third_phase":"11/15 (73%)","shots_outside_box":0,"final_third_entries":8,"touches_in_penalty_area":7},"home":{"duels":64,"fouls":2,"passes":47,"crosses":"2/3 (67%)","tackles":3,"dribbles":"2/4 (50%)","throw_ins":7,"clearances":5,"free_kicks":3,"goal_kicks":1,"long_balls":"3/7 (43%)","recoveries":4,"tackles_won":67,"total_shots":0,"aerial_duels":"2/3 (67%)","dispossessed":0,"ground_duels":"7/11 (64%)","hit_woodwork":0,"blocked_shots":0,"total_tackles":3,"expected_goals":0.0,"accurate_passes":32,"ball_possession":42,"shots_on_target":0,"shots_inside_box":0,"shots_off_target":0,"final_third_phase":"6/11 (55%)","shots_outside_box":0,"final_third_entries":2,"touches_in_penalty_area":5},"first_half":{"away":{"duels":40,"fouls":3,"passes":68,"crosses":"1/3 (33%)","tackles":2,"dribbles":"0/1 (0%)","throw_ins":4,"clearances":5,"free_kicks":2,"goal_kicks":1,"long_balls":"9/14 (64%)","recoveries":9,"tackles_won":100,"total_shots":2,"aerial_duels":"1/3 (33%)","dispossessed":2,"ground_duels":"5/12 (42%)","hit_woodwork":0,"blocked_shots":2,"total_tackles":2,"expected_goals":0.16,"accurate_passes":57,"ball_possession":58,"shots_on_target":0,"shots_inside_box":2,"shots_off_target":0,"shots_outside_box":0,"final_third_entries":8},"home":{"duels":64,"fouls":2,"passes":47,"crosses":"2/3 (67%)","tackles":3,"dribbles":"2/4 (50%)","throw_ins":7,"clearances":5,"free_kicks":3,"goal_kicks":1,"long_balls":"3/7 (43%)","recoveries":4,"tackles_won":67,"total_shots":0,"aerial_duels":"2/3 (67%)","dispossessed":0,"ground_duels":"7/11 (64%)","hit_woodwork":0,"blocked_shots":0,"total_tackles":3,"expected_goals":0.0,"accurate_passes":32,"ball_possession":42,"shots_on_target":0,"shots_inside_box":0,"shots_off_target":0,"shots_outside_box":0,"final_third_entries":2}}}}]