{"count":2,"next":null,"previous":null,"results":[{"id":9061,"api_id":15888684,"league":{"id":31,"api_id":851,"name":"International Friendly Games","country":"International","season_id":87155},"home_team":"Barbados","away_team":"Saint Vincent and the Grenadines","home_team_obj":{"id":681,"api_id":21808,"name":"Barbados","short_name":"Barbados","country":"Barbados"},"away_team_obj":{"id":691,"api_id":21821,"name":"Saint Vincent and the Grenadines","short_name":"Saint Vincent and the Grenadines","country":"Saint Vincent and the Grenadines"},"event_date":"2026-03-30T00:00:00+04:00","status":"2nd_half","home_score":2,"away_score":3,"current_minute":94,"period":"2T","incidents":[{"type":"goal","minute":80,"player":"O. Anderson","is_home":false,"goal_type":"regular","player_id":797258,"away_score":3,"home_score":2},{"type":"goal","minute":60,"player":"Unknown","is_home":true,"goal_type":"regular","player_id":null,"away_score":2,"home_score":2},{"type":"card","minute":52,"player":"Unknown","is_home":false,"card_type":"yellow","player_id":null},{"type":"goal","minute":51,"player":"Unknown","is_home":true,"goal_type":"regular","player_id":null,"away_score":2,"home_score":1},{"type":"card","minute":41,"player":"Unknown","is_home":false,"card_type":"yellow","player_id":null},{"type":"goal","minute":39,"player":"A. Solomon","is_home":false,"goal_type":"regular","player_id":1006444,"away_score":2,"home_score":0},{"type":"goal","minute":28,"player":"K. Franklyn","is_home":false,"goal_type":"regular","player_id":1568568,"away_score":1,"home_score":0},{"type":"card","minute":25,"player":"Unknown","is_home":true,"card_type":"yellow","player_id":null}],"live_stats":null},{"id":9062,"api_id":15888685,"league":{"id":31,"api_id":851,"name":"International Friendly Games","country":"International","season_id":87155},"home_team":"British Virgin Islands","away_team":"Anguilla","home_team_obj":{"id":687,"api_id":21810,"name":"British Virgin Islands","short_name":"British Virgin Islands","country":"British Virgin Islands"},"away_team_obj":{"id":685,"api_id":21804,"name":"Anguilla","short_name":"Anguilla","country":"Anguilla"},"event_date":"2026-03-30T01:30:00+04:00","status":"1st_half","home_score":1,"away_score":0,"current_minute":23,"period":"1T","incidents":[{"type":"goal","minute":6,"player":"Unknown","is_home":true,"goal_type":"regular","player_id":null,"away_score":0,"home_score":1}],"live_stats":null}]}